{
  "title": "HTC One X Wallpapers HD",
  "playStoreURL": "https://play.google.com/store/apps/details?id=com.dessertapps.app.htconexwallpapers",
  "category": "Entertainment",
  "price": "Free",
  "datePublished": "July 2, 2013",
  "version": "1.0.9",
  "operatingSystems": "1.5 and up",
  "ratingsCount": "1468",
  "rating": "3.918256",
  "contentRating": "Low Maturity",
  "creator": "DessertApps",
  "creatorURL": "https://play.google.com/store/apps/details?id=com.dessertapps.app.htconexwallpapers",
  "extendedInfo": {
    "installSize": "709k",
    "downloadsCount": "100,000+",
    "downloadsCountText": "100,000 - 500,000",
    "description": "HTC One X Wallpapers for Android Phones and Galaxy Note and tablets.These images are high quality hd background images for Android Devices.Backgrounds are compatible for all screen size device designed for HTC One X Phone.High Definition wallpapers Backgrounds can be set as your home screen wallpaper.FAQ: 1.HOW TO DOWNLOAD IMAGE SD CARD?NO NEED TO DOWNLOAD THE IMAGES TO SD CARD ALL IMAGES ARE AUTOMATICALLY SAVED TO SD CARD ONLY THING YOU NEED TO KEEP USING APPLICATION TO SET WALLPAPER TO YOUR HOME SCREEN.APPLICATION WILL NOT DOWNLOAD THE IMAGES EVERY LAUNCH IT WILL BE CACHED IN SD CARD WITHOUT INTERNET CONNECTION APPLICATION WILL WORK.2.DOESN'T WORK AT ALL?PRESS MENU KEY SELECT REFRESH TO DOWNLOAD IMAGE FEED.3.IMAGES NOT DOWNLOADING AND LOADING VERY SLOW?PLEASE BE PATIENCE AND LOAD ALL IMAGES BY SCROLLING AND KEEP USING WITHOUT INTERNET CONNECTION. AS THIS IS HD IMAGES WILL TAKE TIME TO DOWNLOAD IN 2G INTERNET CONNECTION. IMAGES SIZE ARE 100KB TO 150KB. IN 3G AND WiFi CONNECTION TO DOWNLOAD EACH IMAGES WILL WILL TAKE AVERAGE TIME 5 Sec.Thanks For downloading HTC One X Wallpapers HD, Please Rate it.Disclaimer:This app is supported via Airpush SDK 5.0. Please note that the following will be added to your device once you download the app – icon ads in home screen and push notification ads in your phone notification bar. You can clear the notification ads/delete home screen icon ads easily. This is a way to make money from this app and giving it to you for free. Thank you for your understanding.",
    "reviews": [
      {
        "documentVersion": "1.0.9",
        "timestampMsec": "1373351614409",
        "starRating": "5",
        "title": "Cant be bad",
        "comment": "Its good",
        "commentId": "gp:AOqpTOH30MQHnoK6URtsi2mx8-VACX96LWvcrIAkRI60082Uy4DnIokjBIgaxqnPUDIRuSLMJgmI1jOu4thEHoU",
        "author": "kunal vashishth",
        "authorURL": "http://lh5.ggpht.com/RREE0f2gSFRq9Yi_umALXt_ML6nJbTYJ6TEsCJg-75c1TUjH4nqP0KNfOsDqxaa_CqY",
        "authorSecureURL": "https://lh5.ggpht.com/RREE0f2gSFRq9Yi_umALXt_ML6nJbTYJ6TEsCJg-75c1TUjH4nqP0KNfOsDqxaa_CqY"
      },
      {
        "documentVersion": "1.0.9",
        "timestampMsec": "1376332400704",
        "starRating": "1",
        "comment": "Crap crap",
        "commentId": "lg:AOqpTOFi5VT_c_ANgFuANKtVTUbJEonT6dRzxcBQa5uK30YxdiZE9bHYirU6DVCiq5h8vo4Oshv1XKEaOEgYq7c",
        "author": "A Google User",
        "authorURL": "http://lh5.ggpht.com/RREE0f2gSFRq9Yi_umALXt_ML6nJbTYJ6TEsCJg-75c1TUjH4nqP0KNfOsDqxaa_CqY"
      },
      {
        "documentVersion": "1.0.9",
        "timestampMsec": "1377159162839",
        "starRating": "5",
        "title": "Good",
        "comment": "I like it.",
        "commentId": "gp:AOqpTOH7bax5NPChMLOspNVvGQ1WqFv01EbefhUbr63CWLA9JAhVC-vrXtjkVdPNrmV3YIe31JYmCAhDEKGEOHk",
        "author": "gursewak singh",
        "authorURL": "http://lh5.ggpht.com/RREE0f2gSFRq9Yi_umALXt_ML6nJbTYJ6TEsCJg-75c1TUjH4nqP0KNfOsDqxaa_CqY",
        "authorSecureURL": "https://lh5.ggpht.com/RREE0f2gSFRq9Yi_umALXt_ML6nJbTYJ6TEsCJg-75c1TUjH4nqP0KNfOsDqxaa_CqY"
      },
      {
        "documentVersion": "1.0.9",
        "timestampMsec": "1378392918229",
        "starRating": "3",
        "title": "HTC rhyme",
        "comment": "Nice wallpapers",
        "commentId": "gp:AOqpTOE_byAtluSbVfEmHaZf8CW8fCPqx6-w77vuN9Wm1S8RHItKcLR6SYT5FLl8PPFsXI-qqD5LPIapL6lQrdc",
        "author": "Rohit Ror",
        "authorURL": "http://lh5.ggpht.com/RREE0f2gSFRq9Yi_umALXt_ML6nJbTYJ6TEsCJg-75c1TUjH4nqP0KNfOsDqxaa_CqY",
        "authorSecureURL": "https://lh5.ggpht.com/RREE0f2gSFRq9Yi_umALXt_ML6nJbTYJ6TEsCJg-75c1TUjH4nqP0KNfOsDqxaa_CqY"
      },
      {
        "documentVersion": "1.0.9",
        "timestampMsec": "1374261413499",
        "starRating": "3",
        "title": "Good",
        "comment": "Going",
        "commentId": "gp:AOqpTOFZx0R1RqLiaBbshlIjb4aOmN4hAM3dXbi2HK790lLX-Z0IBO-rnQJO1VbeQa32AXAusGjrb-oZqaXf88s",
        "author": "awais mir",
        "authorURL": "http://lh3.googleusercontent.com/-KRKhwjtOSHQ/AAAAAAAAAAI/AAAAAAAAADg/3waK-enpUWc/photo.jpg",
        "authorSecureURL": "https://lh3.googleusercontent.com/-KRKhwjtOSHQ/AAAAAAAAAAI/AAAAAAAAADg/3waK-enpUWc/photo.jpg"
      },
      {
        "documentVersion": "1.0.9",
        "timestampMsec": "1374930405085",
        "starRating": "5",
        "comment": "Good",
        "commentId": "gp:AOqpTOFkkA_3MHaRlB4_wOb_lgR8wanx34SBXUrn4qGcz7BGKSzL1OjnKiKKJMk4cLn63GJ6sLz6cZNGhdN-fzU",
        "author": "siva kumar",
        "authorURL": "http://lh3.googleusercontent.com/-VfOoFbBBl8g/AAAAAAAAAAI/AAAAAAAAAs8/a2SzkCVU_KU/photo.jpg",
        "authorSecureURL": "https://lh3.googleusercontent.com/-VfOoFbBBl8g/AAAAAAAAAAI/AAAAAAAAAs8/a2SzkCVU_KU/photo.jpg"
      },
      {
        "documentVersion": "1.0.9",
        "timestampMsec": "1378795775788",
        "starRating": "5",
        "comment": "Goood",
        "commentId": "gp:AOqpTOEl11NtSPsJGUacgsiAwMDYPzlxKlXbu0BQQOUW47KgNSClk16mgNxIb0iCYosPjXNvyGrWS7-poGUQJGE",
        "author": "Santosh Babar",
        "authorURL": "http://lh5.ggpht.com/RREE0f2gSFRq9Yi_umALXt_ML6nJbTYJ6TEsCJg-75c1TUjH4nqP0KNfOsDqxaa_CqY",
        "authorSecureURL": "https://lh5.ggpht.com/RREE0f2gSFRq9Yi_umALXt_ML6nJbTYJ6TEsCJg-75c1TUjH4nqP0KNfOsDqxaa_CqY"
      },
      {
        "documentVersion": "1.0.9",
        "timestampMsec": "1377924917292",
        "starRating": "5",
        "title": "Good",
        "comment": "Good",
        "commentId": "gp:AOqpTOF8utVX49YWRi1mXou5sY15hyQWytt7AFkdjcp9V4ACLhT049BgS0-IxCtkxtoyYb-QVHzvFnPAf31FcEA",
        "author": "Abhay Biswas",
        "authorURL": "http://lh5.ggpht.com/RREE0f2gSFRq9Yi_umALXt_ML6nJbTYJ6TEsCJg-75c1TUjH4nqP0KNfOsDqxaa_CqY",
        "authorSecureURL": "https://lh5.ggpht.com/RREE0f2gSFRq9Yi_umALXt_ML6nJbTYJ6TEsCJg-75c1TUjH4nqP0KNfOsDqxaa_CqY"
      },
      {
        "documentVersion": "1.0.9",
        "timestampMsec": "1376909587473",
        "starRating": "5",
        "comment": "Athar",
        "commentId": "lg:AOqpTOFLPYj0l7M40r3OTzAoBi4BkQ9WhfYuPJCzv3ZxNwStBUhdod-Zdt4yAYkh1vfAXE6ktRZO5o2FaDOS3Vk",
        "author": "A Google User",
        "authorURL": "http://lh5.ggpht.com/RREE0f2gSFRq9Yi_umALXt_ML6nJbTYJ6TEsCJg-75c1TUjH4nqP0KNfOsDqxaa_CqY"
      },
      {
        "documentVersion": "1.0.9",
        "timestampMsec": "1377461537931",
        "starRating": "5",
        "comment": "Wow",
        "commentId": "gp:AOqpTOEGsnnssXu49AH0m6BPZD54B31-ZB7lud6-Csyzr3lt97LZCqamfj_tfLwX1V5VJHLejBOHxitvoOWLkqs",
        "author": "Satyajit Singha",
        "authorURL": "http://lh6.googleusercontent.com/-2sf-xom5XGs/AAAAAAAAAAI/AAAAAAAAAE0/elitM0GRKfk/photo.jpg",
        "authorSecureURL": "https://lh6.googleusercontent.com/-2sf-xom5XGs/AAAAAAAAAAI/AAAAAAAAAE0/elitM0GRKfk/photo.jpg"
      },
      {
        "documentVersion": "1.0.8",
        "timestampMsec": "1367200032461",
        "starRating": "5",
        "title": "Just nice",
        "comment": "Its not real ly cool but i give 5 star",
        "commentId": "gp:AOqpTOHfWfb9wQ62JoBvIcH8espEYzOKee5_a7UUq99gEK4qHWwKLSWOEq0VJDFC6EHrt8XtG-9vIDV2tC06DOY",
        "author": "A Google User",
        "authorURL": "http://lh5.ggpht.com/RREE0f2gSFRq9Yi_umALXt_ML6nJbTYJ6TEsCJg-75c1TUjH4nqP0KNfOsDqxaa_CqY"
      },
      {
        "documentVersion": "1.0.8",
        "timestampMsec": "1371549213761",
        "starRating": "5",
        "title": "Amazing wallpapers.",
        "comment": "I like them.",
        "commentId": "gp:AOqpTOGinozqv_pgYgNWncCKaVLBoOBAsjYHuwMCoXnQtjf7ksmvO9_qvCvXxOcqjGDdxVHpgoIi1zUO6qrQR74",
        "author": "Prosper Eric",
        "authorURL": "http://lh5.ggpht.com/RREE0f2gSFRq9Yi_umALXt_ML6nJbTYJ6TEsCJg-75c1TUjH4nqP0KNfOsDqxaa_CqY",
        "authorSecureURL": "https://lh5.ggpht.com/RREE0f2gSFRq9Yi_umALXt_ML6nJbTYJ6TEsCJg-75c1TUjH4nqP0KNfOsDqxaa_CqY"
      },
      {
        "documentVersion": "1.0.8",
        "timestampMsec": "1372593528280",
        "starRating": "5",
        "title": "Y \\'ll not want for more.",
        "comment": "One for every day and then some !,,",
        "commentId": "gp:AOqpTOFBrlX6gvyPkyL7VGyUbhmjtY8FREOvZ0GS5mVdgH0GagJiWyKUEIZaPlHfvQj0AZxJcoWWgzNNfICDt3s",
        "author": "Trent Wood",
        "authorURL": "http://lh5.ggpht.com/RREE0f2gSFRq9Yi_umALXt_ML6nJbTYJ6TEsCJg-75c1TUjH4nqP0KNfOsDqxaa_CqY",
        "authorSecureURL": "https://lh5.ggpht.com/RREE0f2gSFRq9Yi_umALXt_ML6nJbTYJ6TEsCJg-75c1TUjH4nqP0KNfOsDqxaa_CqY"
      },
      {
        "documentVersion": "1.0.8",
        "timestampMsec": "1368841945634",
        "starRating": "1",
        "title": "Ads in notifications",
        "comment": "I know developers need ads but not in my notifications while the app is not open.",
        "commentId": "gp:AOqpTOGl1ljEpyGhYp36eY_lg_DTUuzwaS_rTVoaUr3TgNhuJQPpRvj0igP08SkXURlPT0dQSNq6q0nlX6RKnP8",
        "author": "James Betoney",
        "authorURL": "http://lh5.googleusercontent.com/-i2-cWFbwzRo/AAAAAAAAAAI/AAAAAAAAAfA/HILtC7daW2w/photo.jpg",
        "authorSecureURL": "https://lh5.googleusercontent.com/-i2-cWFbwzRo/AAAAAAAAAAI/AAAAAAAAAfA/HILtC7daW2w/photo.jpg"
      },
      {
        "documentVersion": "1.0.8",
        "timestampMsec": "1368359665601",
        "starRating": "5",
        "title": "Beautiful pics",
        "comment": "I like it nice wallpapers",
        "commentId": "gp:AOqpTOHMmmXjlrFHnIDt5dbiFs_Sx45q9LimGUDfSxVmT7yx2hFdI_quoTR4Mkk2CT5IRvgt2yZlmqcUUAEmuog",
        "author": "s nawaz baloch",
        "authorURL": "http://lh6.googleusercontent.com/-d2SQbLMqlys/AAAAAAAAAAI/AAAAAAAAAKw/zv0JgMrbOog/photo.jpg",
        "authorSecureURL": "https://lh6.googleusercontent.com/-d2SQbLMqlys/AAAAAAAAAAI/AAAAAAAAAKw/zv0JgMrbOog/photo.jpg"
      },
      {
        "documentVersion": "1.0.8",
        "timestampMsec": "1370994721337",
        "starRating": "5",
        "comment": "Cool pics",
        "commentId": "lg:AOqpTOFku_nxYPY2LpPIjFugJGc8-KTqOwfpp-2jgUiHiwHpyrf7In3WTUHUrJWyPQjtMmZxiTqzsnnQ5K3PRtE",
        "author": "A Google User",
        "authorURL": "http://lh5.ggpht.com/RREE0f2gSFRq9Yi_umALXt_ML6nJbTYJ6TEsCJg-75c1TUjH4nqP0KNfOsDqxaa_CqY"
      },
      {
        "documentVersion": "1.0.8",
        "timestampMsec": "1372182087922",
        "starRating": "4",
        "title": "Gud one",
        "comment": "Semc  Xperia tipo",
        "commentId": "gp:AOqpTOGLcGTueobRl3vhI9-Yx52NIcZGpMJy8r22cYW00-9BO2Qoy-ROnWxYi-CGJ0LS4C9E14UEpQlI4p01T5U",
        "author": "midhun jayakumar",
        "authorURL": "http://lh5.ggpht.com/RREE0f2gSFRq9Yi_umALXt_ML6nJbTYJ6TEsCJg-75c1TUjH4nqP0KNfOsDqxaa_CqY",
        "authorSecureURL": "https://lh5.ggpht.com/RREE0f2gSFRq9Yi_umALXt_ML6nJbTYJ6TEsCJg-75c1TUjH4nqP0KNfOsDqxaa_CqY"
      },
      {
        "documentVersion": "1.0.8",
        "timestampMsec": "1369964219616",
        "starRating": "5",
        "title": "Good",
        "comment": "This is a good one....Go for it..",
        "commentId": "gp:AOqpTOHpFXXtq27uO88bwocuax0FoueimcZYvHLKJ9Dia423R0NbWrUvzJcABCSZN0Py_Gdq5D6UMroFFIuag-c",
        "author": "Mohan Krishna",
        "authorURL": "http://lh4.googleusercontent.com/-kgbBwscgiyA/AAAAAAAAAAI/AAAAAAAAAD8/2wmKFhcFtQM/photo.jpg",
        "authorSecureURL": "https://lh4.googleusercontent.com/-kgbBwscgiyA/AAAAAAAAAAI/AAAAAAAAAD8/2wmKFhcFtQM/photo.jpg"
      },
      {
        "documentVersion": "1.0.8",
        "timestampMsec": "1369191284493",
        "starRating": "3",
        "comment": "Wallppers will be not set at any time when internet connection is not active\\n%%%%%-R@/\\\\/@-%%%%%",
        "commentId": "lg:AOqpTOH6KKF0QGvd4gy6dudA8eo3sU1y5zW2vVNYnC5edfPIU20ckkbbWDz9xdEpc-XUsdrft5GLXtORF215IBo",
        "author": "A Google User",
        "authorURL": "http://lh5.ggpht.com/RREE0f2gSFRq9Yi_umALXt_ML6nJbTYJ6TEsCJg-75c1TUjH4nqP0KNfOsDqxaa_CqY"
      },
      {
        "documentVersion": "1.0.8",
        "timestampMsec": "1368266156357",
        "starRating": "5",
        "title": "I c",
        "comment": "Nice",
        "commentId": "gp:AOqpTOGnHvFDY8qOmq8RA_akY__m3bc1pBKpFxQoO8wXwY7vj5NXlj1K14RC_tBvkhNBdmfjX5eI-a-m0bRYADE",
        "author": "NAZIM Saifi",
        "authorURL": "http://lh6.googleusercontent.com/-d_ep0YU09QY/AAAAAAAAAAI/AAAAAAAAABQ/F0DS1yfiILU/photo.jpg",
        "authorSecureURL": "https://lh6.googleusercontent.com/-d_ep0YU09QY/AAAAAAAAAAI/AAAAAAAAABQ/F0DS1yfiILU/photo.jpg"
      }
    ],
    "permissions": [
      "android.permission.INTERNET",
      "android.permission.WRITE_EXTERNAL_STORAGE",
      "android.permission.ACCESS_WIFI_STATE",
      "android.permission.READ_PHONE_STATE",
      "com.android.browser.permission.WRITE_HISTORY_BOOKMARKS",
      "com.android.browser.permission.READ_HISTORY_BOOKMARKS",
      "com.android.launcher.permission.UNINSTALL_SHORTCUT",
      "com.android.launcher.permission.READ_SETTINGS",
      "android.permission.SET_WALLPAPER",
      "android.permission.RECEIVE_BOOT_COMPLETED",
      "com.android.launcher.permission.INSTALL_SHORTCUT",
      "android.permission.WAKE_LOCK",
      "android.permission.ACCESS_NETWORK_STATE",
      "android.permission.READ_EXTERNAL_STORAGE"
    ]
  }
}
