{
  "title": "Best Islamic Wallpapers",
  "playStoreURL": "https://play.google.com/store/apps/details?id=com.peaksel.bestislamicappswallpapers",
  "category": "Lifestyle",
  "price": "Free",
  "datePublished": "August 16, 2013",
  "version": "2.2.2",
  "operatingSystems": "2.1 and up",
  "ratingsCount": "328",
  "rating": "4.118902",
  "contentRating": "Low Maturity",
  "creator": "Peaksel",
  "creatorURL": "https://play.google.com/store/apps/details?id=com.peaksel.bestislamicappswallpapers",
  "extendedInfo": {
    "installSize": "6.2M",
    "downloadsCount": "100,000+",
    "downloadsCountText": "100,000 - 500,000",
    "description": "Be proud that you are Muslim and show that to the world! Download FREE Best Islamic Wallpapers application and persoanlize your android phone in that way! This is the a beautiful collection of high quality islamic pictures. Find the background you like the most and set it on your home screen. You can see the beautiful islamic wallpaper from Muhammad ibn Abdullah feature a clean look and a strong expression: I am Proud to be Muslim!Check out a creative work  with calligraphic art using arabic letters to form a camel. The calligraphy is set in green wallpaper image with a tree and two of the animals. There is also a beautiful work that features the calligraphic style of the name of the Prophet of Islam: Muhammad. The arabic rendering is put in the middle of a spotlight. The arabic script itself also casts shadows to the surrounding.Then a modified wallpaper that features egyptian skylines with its famous pyramid and mosques. The desert takes the foreground. The clouds in the sky adds the dreamy mood of the scene.The Ka’bah is rendered beautifully in one of the hajj and eid ul adha wallpaper. A supplicating hand wishes for the islamic occasionsl. The dark blue sky in the background is adorned with crescent moon. One renders a beautiful horizon of ka’bah with buildings or skylines in the background. The golden yellow of the sky adds the beauty of this picture.You can congratulate your family or friends returning from Hajj with one beautiful Hajj Mabroor wallpaper.Salah ad-Din (Saladin) was the famous King that campaigned against the Crusaders and freed Jerusalem. He has built this great Citadel overlooking the city of Kairo, Egypt. This wallpaper is a beautiful photograph of this Citadel – which the inside looks like a mosqueOrange wallpaper featuring a calligraphic ornament of the arabic phrase: “Allahu Akbar” (Allah is the Greatest). The picture also adorned with flower and swirl ornaments. Beautiful art for your android phone home screen.Green wallpaper to show that Islam is a way of life. It has a heart to show love to islam and arabic sentence showing the first tenet of islam: There is no god but Allah, Muhammad is the messenger of Allah.A beautiful expression of love to the Messenger of Allah, Muhammad, pbuh in the form of a colorful wallpaper. فداك قلبي يارسول الله this arabic expression means ransom my heart or my heart is for you, o messenger of Allah.There is a calligraphic wallpaper that takes the call of prayer (athan) and transform it into a beautiful wallpaper with white and blue colors. The wallpaper has also a mosque in the background and a hadith: “there is no Muslim that prostrates to God except that God raises him one degree in Paradise by it and forgives for him a sin.”This red wallpaper by Muhammad is a typography of the 99 names of Allah or Asmaul Husna forming the word of Allah in arabic. A nice art work, simple and creative!Asmaul Husna or the Beautiful Names of Allah are 99 names or attributes of Allah that muslims encouraged to remember and supplicate with them. This wallpaper lists all those names in a beautiful arrangement with pastel colors.One image shows in golden arabic writing one verse from the Qur’an that praise the characters of our beloved Prophet Muhammad.Allah is The Light of the Heaven Wallpaper and many other beautiful Islamic images thet are a real work of art.Features of wallpapers app:- Works offline - no internet connection required after you download once.- App 2 SD card support.- Share app on Facebook, Twitter, send by bluetooth, send by gmail, save to Dropbox and more.- Free and always will beThis free app may contain ads in notification tray and may create internet shortcuts on your desktop. Shortcut icons can be deleted with no effect to this app. If you want to stop receiving notification(s), please go to http://www.unpush.me and http://opt.leadbolt.com/. Banner ads (if any), cannot be removed.",
    "reviews": [
      {
        "documentVersion": "2.2.2",
        "timestampMsec": "1377354544941",
        "starRating": "5",
        "title": "Shabbir",
        "comment": "Great app",
        "commentId": "gp:AOqpTOF6-Bc3yNVZ0DnBJm95aO3JBtnhnQhu0lqtDhvlDpIa8OX4NNZEAuBTBiWQ2n5IdL8LhwwE4MHWy-sWgns",
        "author": "shabbir panjesha",
        "authorURL": "http://lh4.googleusercontent.com/-7i9lHYTct-w/AAAAAAAAAAI/AAAAAAAAAZQ/DfXEHkApQcU/photo.jpg",
        "authorSecureURL": "https://lh4.googleusercontent.com/-7i9lHYTct-w/AAAAAAAAAAI/AAAAAAAAAZQ/DfXEHkApQcU/photo.jpg"
      },
      {
        "documentVersion": "2.2.2",
        "timestampMsec": "1378267761067",
        "starRating": "5",
        "title": "Ya Allah",
        "comment": "5 start ya Allah",
        "commentId": "gp:AOqpTOGKLmmLHlholri7_cbdOR36lCvuQm51asZEqgcdsWEAFAWwC0aA0fnd-l1WFoLBPcSiCPdhWhqk2D0Prpo",
        "author": "My heart",
        "authorURL": "http://lh5.ggpht.com/RREE0f2gSFRq9Yi_umALXt_ML6nJbTYJ6TEsCJg-75c1TUjH4nqP0KNfOsDqxaa_CqY",
        "authorSecureURL": "https://lh5.ggpht.com/RREE0f2gSFRq9Yi_umALXt_ML6nJbTYJ6TEsCJg-75c1TUjH4nqP0KNfOsDqxaa_CqY"
      },
      {
        "documentVersion": "2.2.1",
        "timestampMsec": "1375796317436",
        "starRating": "4",
        "title": "Love",
        "comment": "Like it",
        "commentId": "gp:AOqpTOGVMVNzKQRYbwM5XWc3Tcz4hfJCzyXIh5IuBFRv0mHM628QatSEzAUEm2L5xz_vK-q5AWsu-AQPHzlJF4Q",
        "author": "iftekar kotwal",
        "authorURL": "http://lh5.ggpht.com/RREE0f2gSFRq9Yi_umALXt_ML6nJbTYJ6TEsCJg-75c1TUjH4nqP0KNfOsDqxaa_CqY",
        "authorSecureURL": "https://lh5.ggpht.com/RREE0f2gSFRq9Yi_umALXt_ML6nJbTYJ6TEsCJg-75c1TUjH4nqP0KNfOsDqxaa_CqY"
      },
      {
        "documentVersion": "2.2.1",
        "timestampMsec": "1376701441435",
        "starRating": "5",
        "comment": "Five",
        "commentId": "gp:AOqpTOFi7235WvdLXKiQY8k415aA7unz1iAbAzOB1BZ5PppTOde0NxVQRt8MHkNZ0AbXEAG6AFDawes5e2wsZ28",
        "author": "azhar uddin",
        "authorURL": "http://lh6.googleusercontent.com/-_RCuG8BDWd8/AAAAAAAAAAI/AAAAAAAAABY/iY_Hjr3vrh8/photo.jpg",
        "authorSecureURL": "https://lh6.googleusercontent.com/-_RCuG8BDWd8/AAAAAAAAAAI/AAAAAAAAABY/iY_Hjr3vrh8/photo.jpg"
      },
      {
        "timestampMsec": "1374850051479",
        "starRating": "5",
        "title": "MashaAllah goodwork...",
        "comment": "May Allahs blessings be on you...",
        "commentId": "gp:AOqpTOFsXO54gXN-Y488sGNTJ-dpU9gnLlxbh5Qc4YxD2x5JvihV-pXqmk6QpaeccrlioxQobQ3dqM-OcjB_CKQ",
        "author": "Sayed Nadimul Ahasan",
        "authorURL": "http://lh5.ggpht.com/RREE0f2gSFRq9Yi_umALXt_ML6nJbTYJ6TEsCJg-75c1TUjH4nqP0KNfOsDqxaa_CqY",
        "authorSecureURL": "https://lh5.ggpht.com/RREE0f2gSFRq9Yi_umALXt_ML6nJbTYJ6TEsCJg-75c1TUjH4nqP0KNfOsDqxaa_CqY"
      },
      {
        "timestampMsec": "1369137178561",
        "starRating": "5",
        "title": "Sony xperia j",
        "comment": "Super it is best",
        "commentId": "gp:AOqpTOHVzY6hnJ2yhW9wJDpSD8djSKGHruE0bn3y4rFCudQTq7U5TnwMzYuZXadLWlUBhrBfe6PLrV0J_M871cA",
        "author": "A Google User",
        "authorURL": "http://lh5.ggpht.com/RREE0f2gSFRq9Yi_umALXt_ML6nJbTYJ6TEsCJg-75c1TUjH4nqP0KNfOsDqxaa_CqY"
      },
      {
        "timestampMsec": "1371647024193",
        "starRating": "5",
        "title": "Allohuakbar",
        "comment": "Like it",
        "commentId": "gp:AOqpTOFsarofwsC9n_hyRLhJ8t03pq5FG6qKlR7XEQfnBaoEmocx2BrVzvgTUOyvuvhRYwhVIxPdjXv0DjQIgCc",
        "author": "dadang achmad",
        "authorURL": "http://lh4.googleusercontent.com/-sfJQ4NSmJQA/AAAAAAAAAAI/AAAAAAAABhM/jes_dGctpzU/photo.jpg",
        "authorSecureURL": "https://lh4.googleusercontent.com/-sfJQ4NSmJQA/AAAAAAAAAAI/AAAAAAAABhM/jes_dGctpzU/photo.jpg"
      },
      {
        "timestampMsec": "1369369565038",
        "starRating": "5",
        "title": "nice",
        "comment": "wondarfullll",
        "commentId": "gp:AOqpTOEGB6GgYvKatPAxWFP1tvS3RUQ2UkyYNIPEEU_XETtGjAf7Uo2Z9TgFboNRFfGghAQrHqxI10PmeH8s7CI",
        "author": "Bacha Khan",
        "authorURL": "http://lh5.ggpht.com/RREE0f2gSFRq9Yi_umALXt_ML6nJbTYJ6TEsCJg-75c1TUjH4nqP0KNfOsDqxaa_CqY",
        "authorSecureURL": "https://lh5.ggpht.com/RREE0f2gSFRq9Yi_umALXt_ML6nJbTYJ6TEsCJg-75c1TUjH4nqP0KNfOsDqxaa_CqY"
      },
      {
        "timestampMsec": "1363568301282",
        "starRating": "5",
        "title": "Great",
        "comment": "Really great !!  I like it  \\\" ALLAH akbar \\\"",
        "commentId": "gp:AOqpTOEIXvhkvm1Ap0juNYqFLZ8EyKAvA6Orv2b7MoQN1oO1guCVG2y7pWno9nM9LYIdBNFsVE0gzajFK6D0RBY",
        "author": "Hasnaa Hamed",
        "authorURL": "http://lh5.ggpht.com/RREE0f2gSFRq9Yi_umALXt_ML6nJbTYJ6TEsCJg-75c1TUjH4nqP0KNfOsDqxaa_CqY",
        "authorSecureURL": "https://lh5.ggpht.com/RREE0f2gSFRq9Yi_umALXt_ML6nJbTYJ6TEsCJg-75c1TUjH4nqP0KNfOsDqxaa_CqY"
      },
      {
        "timestampMsec": "1358618657463",
        "starRating": "1",
        "title": "Beware",
        "comment": "It disabled my screen and put ads in my notifications bar.",
        "commentId": "gp:AOqpTOH08mO8RotjxmA-lghYZZ4DlkfVJU-PCFEIDF8YdKK1c-jtg-waEaV6meHrWlZWFQziN7Hkxe6m6A7Quoo",
        "author": "Ibrahim Al-tiay",
        "authorURL": "http://lh4.googleusercontent.com/-HWxfdwqZdZA/AAAAAAAAAAI/AAAAAAAABPI/ZCsyXhSTPWs/photo.jpg",
        "authorSecureURL": "https://lh4.googleusercontent.com/-HWxfdwqZdZA/AAAAAAAAAAI/AAAAAAAABPI/ZCsyXhSTPWs/photo.jpg"
      },
      {
        "timestampMsec": "1351978846210",
        "starRating": "1",
        "title": "Spam app!",
        "comment": "Watch out.! Creates shortcut without permission on your home screen: true adware.",
        "commentId": "lg:AOqpTOGUj7oFT000LUWXGpexSI-GpCsgEcXDgyWOBMfhVXE-gDQXr0OgdCGDXzkMvDGzJN9wHk7WW8yMCz_eaEs",
        "author": "A Google User",
        "authorURL": "http://lh5.ggpht.com/RREE0f2gSFRq9Yi_umALXt_ML6nJbTYJ6TEsCJg-75c1TUjH4nqP0KNfOsDqxaa_CqY"
      },
      {
        "timestampMsec": "1360246066233",
        "starRating": "5",
        "title": "Mastan",
        "comment": "So beautiful photos",
        "commentId": "gp:AOqpTOHKy5jQKaYm46p6gv7CGEhUoOb-v9Ad0DuZiSDX0YMv7Mq5DgRmGbz8HnFcdbHfEVIHRC49nhAtH9Y9TTs",
        "author": "mastan vali",
        "authorURL": "http://lh5.ggpht.com/RREE0f2gSFRq9Yi_umALXt_ML6nJbTYJ6TEsCJg-75c1TUjH4nqP0KNfOsDqxaa_CqY",
        "authorSecureURL": "https://lh5.ggpht.com/RREE0f2gSFRq9Yi_umALXt_ML6nJbTYJ6TEsCJg-75c1TUjH4nqP0KNfOsDqxaa_CqY"
      },
      {
        "timestampMsec": "1349441794529",
        "starRating": "5",
        "title": "Heart wallpapers",
        "comment": "Best",
        "commentId": "lg:AOqpTOFqI_n4yTdFJOblr_mQwSAQQeMYvKBBtTqrTVrqa3wtuspbrTLstVHrep0o-2OAFY44jnoxntuMWz0bkQw",
        "author": "A Google User",
        "authorURL": "http://lh5.ggpht.com/RREE0f2gSFRq9Yi_umALXt_ML6nJbTYJ6TEsCJg-75c1TUjH4nqP0KNfOsDqxaa_CqY"
      },
      {
        "timestampMsec": "1348499532687",
        "starRating": "5",
        "title": "Shafit",
        "comment": "Very superb",
        "commentId": "lg:AOqpTOEsJw3sENNk-Xx4zFCEdDb5h6hDSMUOdMSMVhXrjgsFNFHU5cnoB_3AB-NR1gaE6Iecut02jcXqYlr0jMI",
        "author": "A Google User",
        "authorURL": "http://lh5.ggpht.com/RREE0f2gSFRq9Yi_umALXt_ML6nJbTYJ6TEsCJg-75c1TUjH4nqP0KNfOsDqxaa_CqY"
      },
      {
        "timestampMsec": "1345204882045",
        "starRating": "5",
        "title": "R\\303\\241\\303\\241d",
        "comment": "Fantastic",
        "commentId": "lg:AOqpTOGvZwd-4IhVKTcC1BLH_Ilqvtf-HaRfZiNYaYELjhqTkajlvLJUQAev6rZ9zfrz8nNz8UYl-F54TnVdgb0",
        "author": "A Google User",
        "authorURL": "http://lh5.ggpht.com/RREE0f2gSFRq9Yi_umALXt_ML6nJbTYJ6TEsCJg-75c1TUjH4nqP0KNfOsDqxaa_CqY"
      },
      {
        "timestampMsec": "1345991252634",
        "starRating": "5",
        "title": "Basma",
        "comment": "Mashallah best app evver may allah bless all.. jazakhallah khair",
        "commentId": "lg:AOqpTOFG7EnpGoaT4BRYkS6qIO4oMfz0wgaRX_0SY-o5pdq5zJshwxOhjCtCnShFq6BPDX2nlTMqR4UW2D-O8Rs",
        "author": "A Google User",
        "authorURL": "http://lh5.ggpht.com/RREE0f2gSFRq9Yi_umALXt_ML6nJbTYJ6TEsCJg-75c1TUjH4nqP0KNfOsDqxaa_CqY"
      },
      {
        "timestampMsec": "1373607036792",
        "starRating": "4",
        "title": "Finally",
        "comment": "Mashallah nice wallpapers the ads I would say are less than halal",
        "commentId": "gp:AOqpTOEaTNcsk0L7WEkIrpnIy19-Sl3GELgdvT-x8BMbUe4SUVQQuwdsaZu4w7VPwKqwJg15pAUGYjF6VeB_a6c",
        "author": "Hyder Ahmed",
        "authorURL": "http://lh4.googleusercontent.com/-cCxxdoHPuQ0/AAAAAAAAAAI/AAAAAAAAAHk/X1QtEjQr3yY/photo.jpg",
        "authorSecureURL": "https://lh4.googleusercontent.com/-cCxxdoHPuQ0/AAAAAAAAAAI/AAAAAAAAAHk/X1QtEjQr3yY/photo.jpg"
      },
      {
        "timestampMsec": "1346064032366",
        "starRating": "5",
        "title": "Wonderful",
        "comment": ":)",
        "commentId": "lg:AOqpTOEn29xSnIAAzA3p3_YEyX2jQbxzTJbdThPksYzxfpbjACVohYUzRbq6-nlBRIhGHQLNpFUTof2lu040cXw",
        "author": "A Google User",
        "authorURL": "http://lh5.ggpht.com/RREE0f2gSFRq9Yi_umALXt_ML6nJbTYJ6TEsCJg-75c1TUjH4nqP0KNfOsDqxaa_CqY"
      },
      {
        "timestampMsec": "1343668855555",
        "starRating": "5",
        "title": "Best islamic wallpaper",
        "comment": "very nice",
        "commentId": "lg:AOqpTOHgwV_UD4cZijU1r_cprFQh7BeOfNqhVaDlLF4vhp3Td6wOTlzczsBKZ2yHJnoz1idCMNmwcV1rIPt8UWg",
        "author": "A Google User",
        "authorURL": "http://lh5.ggpht.com/RREE0f2gSFRq9Yi_umALXt_ML6nJbTYJ6TEsCJg-75c1TUjH4nqP0KNfOsDqxaa_CqY"
      },
      {
        "timestampMsec": "1362716785671",
        "starRating": "5",
        "title": "Ahmed ragab",
        "comment": "Very gooood",
        "commentId": "gp:AOqpTOHskiChVHu5zIikJoqekI4Hu4dnat2Y9Jz4hnGap9-uzhZ_y2aDnnZnAQGOO8878sm9XXF-wnXeTND5CGM",
        "author": "Ahmed Ragab",
        "authorURL": "http://lh5.ggpht.com/RREE0f2gSFRq9Yi_umALXt_ML6nJbTYJ6TEsCJg-75c1TUjH4nqP0KNfOsDqxaa_CqY",
        "authorSecureURL": "https://lh5.ggpht.com/RREE0f2gSFRq9Yi_umALXt_ML6nJbTYJ6TEsCJg-75c1TUjH4nqP0KNfOsDqxaa_CqY"
      }
    ],
    "permissions": [
      "android.permission.SET_WALLPAPER",
      "android.permission.ACCESS_WIFI_STATE",
      "android.permission.WAKE_LOCK",
      "android.permission.INTERNET",
      "android.permission.ACCESS_NETWORK_STATE",
      "android.permission.WRITE_EXTERNAL_STORAGE",
      "android.permission.ACCESS_COARSE_LOCATION",
      "android.permission.READ_PHONE_STATE",
      "android.permission.RECEIVE_BOOT_COMPLETED",
      "android.permission.VIBRATE",
      "android.permission.ACCESS_FINE_LOCATION",
      "android.permission.ACCESS_LOCATION_EXTRA_COMMANDS",
      "com.android.launcher.permission.INSTALL_SHORTCUT",
      "com.android.launcher.permission.UNINSTALL_SHORTCUT",
      "com.android.launcher.permission.READ_SETTINGS",
      "android.permission.GET_TASKS",
      "android.permission.READ_EXTERNAL_STORAGE"
    ]
  }
}
