{
  "title": "Shani Mahamantra Collections",
  "playStoreURL": "https://play.google.com/store/apps/details?id=com.expertwebguru.shanimahamantra",
  "category": "Music & Audio",
  "price": "Free",
  "datePublished": "July 20, 2013",
  "version": "5.1",
  "operatingSystems": "2.3 - 4.2",
  "ratingsCount": "47",
  "rating": "4.5531917",
  "contentRating": "Everyone",
  "creator": "expertwebguru",
  "creatorURL": "https://play.google.com/store/apps/details?id=com.expertwebguru.shanimahamantra",
  "extendedInfo": {
    "installSize": "1.5M",
    "downloadsCount": "10,000+",
    "downloadsCountText": "10,000 - 50,000",
    "description": "Listen Shani Dev Mahamantra daily and make your life full of happiness, peaceful.. cool and calm. This app have complete collections of all shani dev maharaj mantra and chalisha with shani mahamantra.BEST FEATURES:1. Listen complete collection of \"SHANI MAHAMANTRA COLLECTIONS\"   with dialogue in easy language.2. You can play  some other audio stream which help shani dev happy.3. You can create your favorite list.4. You can download audio stream and play locally for high quality.5. You can set particular audio stream or downloaded audio as alarm to play particular time ..    for example every morning every evening ....etc.6. You can play sankh and bell to pray.7. You can provide your suggestion to us.8. You can share your friends and family.Note:  Best on Wifi,  3G and for 2G user can download audio stream locally and play with high quality. For any issue please provide your valuable suggestion. Please  rate us with 5 star for motivation to create free apps*******************************************************************************************************                                      FIX ALL ISSUES*******************************************************************************************************There are many gods in our Hindu religion but lord Shani dev is different from them. He has immense power, appeased toward off, evil eye etc. Saturday is the day which is devoted to Lord Shani Dev. Traditionally God Shani Dev is depicted in Hindu mythology as extremely dark wearing black clothes and mounted on a vulture. The basic mantra of Shani dev is “Om Sham Shanaiscaryaye Namah.”Lord Shani Dev who is the son of Surya Dev (Sun) and Chhaya (Suvarna) is also known as one of the nine “Navagraha” by Hindu belief. Lord Shani Dev have a seventh place among these nine planets which govern our lives. Another name of Shani dev is Shanaiscarya, Asita, Saptarchi, Kruralochana, Pangu, etc. The birth place of Lord Shani Dev is Saurashtra, Gujarat. Hindu people believe that he is the god causing miseries in the life of a human being. So, Lord Shani Dev occupies the principal position among the Hindu’s God.!!  Jai Shree Shani Dev   !!    !!    Jai Shree Shani Dev  !!       !!  Jai Shree Shani Dev   !!    !!  Jai Shree Shani Dev  !!",
    "reviews": [
      {
        "timestampMsec": "1375504145268",
        "starRating": "5",
        "title": "Jai shanidev",
        "comment": "Best app.",
        "commentId": "gp:AOqpTOFv0xsBwzSheBNcR99XWSSOK7Tbom7ilH1a7D_0WnE1B2XCZwPG36bMBkmp0Gmfjk2lht30ze2sJqXN3w",
        "author": "Bharat Chavan",
        "authorURL": "http://lh5.ggpht.com/RREE0f2gSFRq9Yi_umALXt_ML6nJbTYJ6TEsCJg-75c1TUjH4nqP0KNfOsDqxaa_CqY",
        "authorSecureURL": "https://lh5.ggpht.com/RREE0f2gSFRq9Yi_umALXt_ML6nJbTYJ6TEsCJg-75c1TUjH4nqP0KNfOsDqxaa_CqY"
      },
      {
        "timestampMsec": "1377328401010",
        "starRating": "5",
        "comment": "Nice",
        "commentId": "gp:AOqpTOFaUXqVVs7LuppvcRQT0oCEpFZpFRCGv7cfIbNALyzmuldGqWgEFkbuwr7MdP1G8djOgMpLZY4hPeuU1A",
        "author": "Kavan Shah",
        "authorURL": "http://lh5.ggpht.com/RREE0f2gSFRq9Yi_umALXt_ML6nJbTYJ6TEsCJg-75c1TUjH4nqP0KNfOsDqxaa_CqY",
        "authorSecureURL": "https://lh5.ggpht.com/RREE0f2gSFRq9Yi_umALXt_ML6nJbTYJ6TEsCJg-75c1TUjH4nqP0KNfOsDqxaa_CqY"
      },
      {
        "timestampMsec": "1366788373351",
        "starRating": "1",
        "title": "Samsung S2",
        "comment": "Worst app. Simply streaming online. Better bookmark some website rather than using this app.",
        "commentId": "gp:AOqpTOHt6KdoM4SQVwko0NyZve_T_rnN4nkWT7maknaCNRY4TdRE_GrCuCBdtoN5PA5Cq0J9jSAJWuZYYaROAA",
        "author": "AK D",
        "authorURL": "http://lh6.googleusercontent.com/-Dad-mHtgXc8/AAAAAAAAAAI/AAAAAAAAObs/T_6zsYm7nn8/photo.jpg",
        "authorSecureURL": "https://lh6.googleusercontent.com/-Dad-mHtgXc8/AAAAAAAAAAI/AAAAAAAAObs/T_6zsYm7nn8/photo.jpg"
      },
      {
        "timestampMsec": "1366682909557",
        "starRating": "1",
        "title": "Live streaming",
        "comment": "Pls don\\'t download... its live streaming from internet... it stops in between and starts buffering...",
        "commentId": "gp:AOqpTOFfzzkzWI0TwEwCeWQuEBQaxTtx_6m5bMxLCgwr7qOeBw4Kab83duJuIzhG24Fjct44vRpuSWGa-o-iFw",
        "author": "A Google User",
        "authorURL": "http://lh5.ggpht.com/RREE0f2gSFRq9Yi_umALXt_ML6nJbTYJ6TEsCJg-75c1TUjH4nqP0KNfOsDqxaa_CqY"
      },
      {
        "timestampMsec": "1371954938938",
        "starRating": "5",
        "title": "I am a devotee of LORD SHANIDEVA",
        "comment": "Thanks to developer for giving such a good app.",
        "commentId": "gp:AOqpTOGQliLdJnYxAQFPpqgaT2e5AALM1pGWIaV-LzJA5uQrcNy4tEI_KQLhbnxmvBHVIB9oMMprsbwi-kBICg",
        "author": "SURESH BABU S A",
        "authorURL": "http://lh5.ggpht.com/RREE0f2gSFRq9Yi_umALXt_ML6nJbTYJ6TEsCJg-75c1TUjH4nqP0KNfOsDqxaa_CqY",
        "authorSecureURL": "https://lh5.ggpht.com/RREE0f2gSFRq9Yi_umALXt_ML6nJbTYJ6TEsCJg-75c1TUjH4nqP0KNfOsDqxaa_CqY"
      },
      {
        "timestampMsec": "1366041585017",
        "starRating": "5",
        "title": "Jai shanidev",
        "comment": "Bahut acha app hai I love shanidev",
        "commentId": "gp:AOqpTOHdIx6CHP7BhInDrUHwYcDMwzikxgQwkV2g2VuRXp53HHMGV7gFQR8dlLY0UDCaxlEat7HGeH_Ma8nvHQ",
        "author": "A Google User",
        "authorURL": "http://lh5.ggpht.com/RREE0f2gSFRq9Yi_umALXt_ML6nJbTYJ6TEsCJg-75c1TUjH4nqP0KNfOsDqxaa_CqY"
      },
      {
        "timestampMsec": "1367698655217",
        "starRating": "5",
        "title": "Superb",
        "comment": "Very very good.",
        "commentId": "gp:AOqpTOECvZ_eQkEl6AdcsqbJNOG_HpdWScJ8-LRwaVQbLmupHOJ9pmcuP20qK50b0MjqkpbYKmBcgE9yloXL-Q",
        "author": "dinesh soni",
        "authorURL": "http://lh4.googleusercontent.com/-xYe26oPYPXo/AAAAAAAAAAI/AAAAAAAABc0/CBrnNDIO_C0/photo.jpg",
        "authorSecureURL": "https://lh4.googleusercontent.com/-xYe26oPYPXo/AAAAAAAAAAI/AAAAAAAABc0/CBrnNDIO_C0/photo.jpg"
      },
      {
        "timestampMsec": "1360544145088",
        "starRating": "1",
        "title": "App not working",
        "comment": "Its always says media error. Please rectify.",
        "commentId": "gp:AOqpTOGhp_55RCTi1pvdY1ke6EX2Wwiv-aMbdXDM2G3gltRjuTYGUsuuW03NJIRIr_7zrXuh9Vc5JQ78PLZfxw",
        "author": "Hemant Pasricha",
        "authorURL": "http://lh4.googleusercontent.com/-6nN0w8keFl4/AAAAAAAAAAI/AAAAAAAAAaU/1dpP1I6gYNo/photo.jpg",
        "authorSecureURL": "https://lh4.googleusercontent.com/-6nN0w8keFl4/AAAAAAAAAAI/AAAAAAAAAaU/1dpP1I6gYNo/photo.jpg"
      },
      {
        "timestampMsec": "1363094448360",
        "starRating": "5",
        "title": "Out standing app",
        "comment": "Wow! It,s  really an amazing app.",
        "commentId": "gp:AOqpTOHElrTaiKsJtadsRyFZ4SSxpFRAC-7bjBEHjYaq-GBvx9Nu9GTQhNwblpwI4Y0CyI9dycgE4tbfShWI7g",
        "author": "rishu yadav",
        "authorURL": "http://lh5.ggpht.com/RREE0f2gSFRq9Yi_umALXt_ML6nJbTYJ6TEsCJg-75c1TUjH4nqP0KNfOsDqxaa_CqY",
        "authorSecureURL": "https://lh5.ggpht.com/RREE0f2gSFRq9Yi_umALXt_ML6nJbTYJ6TEsCJg-75c1TUjH4nqP0KNfOsDqxaa_CqY"
      },
      {
        "timestampMsec": "1360427434313",
        "starRating": "1",
        "title": "Not working",
        "comment": "Its not playing in galaxy fit. Buffering and playing error. Plz help",
        "commentId": "gp:AOqpTOG0Sz86ATepvKcjNPK8bMr6g3hSf1TmlPb_0TLGlwsIt_cRtDGkmQX7g8bQKPoGlV3xuwcjxDrtgXx50g",
        "author": "durgesh chauhan",
        "authorURL": "http://lh5.ggpht.com/RREE0f2gSFRq9Yi_umALXt_ML6nJbTYJ6TEsCJg-75c1TUjH4nqP0KNfOsDqxaa_CqY",
        "authorSecureURL": "https://lh5.ggpht.com/RREE0f2gSFRq9Yi_umALXt_ML6nJbTYJ6TEsCJg-75c1TUjH4nqP0KNfOsDqxaa_CqY"
      },
      {
        "timestampMsec": "1358514828701",
        "starRating": "5",
        "title": "JAI SHANI DEV KI",
        "comment": "OM SHRI SURYA PUTRA SHANI DEVAI NAMAH",
        "commentId": "gp:AOqpTOGFv1m-zdXXC2QLKNBkMbvUb-bDCAI1SSu8cJwrlx_SQ7zCMLU_JCaR6XwBVQ6HuB8hO00qADpoovdrMQ",
        "author": "HITESH SHARMA",
        "authorURL": "http://lh5.ggpht.com/RREE0f2gSFRq9Yi_umALXt_ML6nJbTYJ6TEsCJg-75c1TUjH4nqP0KNfOsDqxaa_CqY",
        "authorSecureURL": "https://lh5.ggpht.com/RREE0f2gSFRq9Yi_umALXt_ML6nJbTYJ6TEsCJg-75c1TUjH4nqP0KNfOsDqxaa_CqY"
      },
      {
        "timestampMsec": "1357929672583",
        "starRating": "5",
        "title": "nice",
        "comment": "gud",
        "commentId": "gp:AOqpTOGClT7EiHwZfsp8voBHx7t8am5x5VoD970TCiGqIghkPIW4TnqY-OgTmv0xHLlfnmTHtwyEph9GUPigRg",
        "author": "Vijay Gosavi",
        "authorURL": "http://lh5.googleusercontent.com/-dAvO-M6FmZU/AAAAAAAAAAI/AAAAAAAAAAA/T2-QHz4af34/photo.jpg",
        "authorSecureURL": "https://lh5.googleusercontent.com/-dAvO-M6FmZU/AAAAAAAAAAI/AAAAAAAAAAA/T2-QHz4af34/photo.jpg"
      }
    ],
    "permissions": [
      "android.permission.READ_PHONE_STATE",
      "android.permission.ACCESS_NETWORK_STATE",
      "android.permission.INTERNET",
      "android.permission.WRITE_EXTERNAL_STORAGE",
      "android.permission.READ_EXTERNAL_STORAGE"
    ]
  }
}
