{
  "title": "Test My 4G Speed Quickly",
  "playStoreURL": "https://play.google.com/store/apps/details?id=com.digitalsummitdesign.testmy4gspeed",
  "category": "Tools",
  "price": "Free",
  "datePublished": "March 11, 2013",
  "version": "1.1",
  "operatingSystems": "2.2 and up",
  "ratingsCount": "5",
  "rating": "3.8",
  "contentRating": "Everyone",
  "creator": "Digital Summit Design",
  "creatorURL": "https://play.google.com/store/apps/details?id=com.digitalsummitdesign.testmy4gspeed",
  "extendedInfo": {
    "installSize": "248k",
    "downloadsCount": "500+",
    "downloadsCountText": "500 - 1,000",
    "description": "Are you getting what you have paid for? By using Test My 4G Speed you can consistently verify if your Internet service provider is delivering the connection speed they promised.This service is 100% FREE and works over both WiFi and cellular networks.It's fast and gets your internet speed faster than any other app. You can test multiple times to get an average speed.",
    "reviews": [
      {
        "timestampMsec": "1375505067055",
        "starRating": "5",
        "comment": "Cool.",
        "commentId": "gp:AOqpTOGw6hr561wYAGpYrNHFSac9q_9aKb7c81kCKfygIULqlCBtW5WVgcpC00KXpPfbrI-FzVm50b0YSP4kmA",
        "author": "Checkina Coulibaly",
        "authorURL": "http://lh4.googleusercontent.com/-RjX-bJCkif8/AAAAAAAAAAI/AAAAAAAAFNw/2pU39dDMESE/photo.jpg",
        "authorSecureURL": "https://lh4.googleusercontent.com/-RjX-bJCkif8/AAAAAAAAAAI/AAAAAAAAFNw/2pU39dDMESE/photo.jpg"
      },
      {
        "timestampMsec": "1365382686311",
        "starRating": "3",
        "title": "Tommie",
        "comment": "ok.\\'",
        "commentId": "gp:AOqpTOEi-nH84vQ1_J-ardUhRG1_kKj8ekFNBLIcSn6Ug2DzXJS7heZP5OzV2qCA7vQwxmqXpoiJc27CfyKsZw",
        "author": "thet myattaw",
        "authorURL": "http://lh5.googleusercontent.com/-S3YK1Sk88Xw/AAAAAAAAAAI/AAAAAAAAABQ/GU3jgysomi0/photo.jpg",
        "authorSecureURL": "https://lh5.googleusercontent.com/-S3YK1Sk88Xw/AAAAAAAAAAI/AAAAAAAAABQ/GU3jgysomi0/photo.jpg"
      }
    ],
    "permissions": [
      "android.permission.INTERNET",
      "android.permission.ACCESS_NETWORK_STATE"
    ]
  }
}
