{
  "title": "CLUSTER Classic White Theme",
  "playStoreURL": "https://play.google.com/store/apps/details?id=com.cluster.kakaotheme.white",
  "category": "Tools",
  "price": "Free",
  "datePublished": "April 22, 2013",
  "version": "1.0",
  "operatingSystems": "1.6 and up",
  "ratingsCount": "33",
  "rating": "5.0",
  "contentRating": "Everyone",
  "creator": "Inerve",
  "creatorURL": "https://play.google.com/store/apps/details?id=com.cluster.kakaotheme.white",
  "extendedInfo": {
    "installSize": "642k",
    "downloadsCount": "5,000+",
    "downloadsCountText": "5,000 - 10,000",
    "description": "CLUSTER Dev에서 만든 세련된 화이트 스타일의 카카오톡 테마입니다.달콤하고 차분한 화이트 색상으로 카카오톡을 새롭게 꾸몄습니다.대부분의 이미지들이 xhdpi (HD 해상도) 기기들이 아닌 hdpi (WVGA 해상도)에 맞춰져있어 HD 해상도 폰들에는 약간의 퀄리티 저하가 보일 수 있습니다.테마 특징- 깔끔하고 달달한 화이트 색상- 세련되면서 은근히 알록달록한 귀여운 색상제작자- 미루 (CLUSTER Dev 소속 디자이너, 팀장)Thanks To- 카카오팀- 전대웅 (스크린샷에 출연해줘서 고맙습니다 ㅋㅋ)----개발자 연락처 :...",
    "reviews": [
      {
        "comment": "No reviews given!"
      }
    ],
    "permissions": [

    ]
  }
}
