{
  "title": "Islam TV",
  "playStoreURL": "https://play.google.com/store/apps/details?id=com.codelixir.islamtv",
  "category": "Media & Video",
  "price": "Free",
  "datePublished": "August 12, 2013",
  "version": "1.2",
  "operatingSystems": "2.1 and up",
  "ratingsCount": "15",
  "rating": "4.4666667",
  "contentRating": "Everyone",
  "creator": "Codelixir Lab",
  "creatorURL": "https://play.google.com/store/apps/details?id=com.codelixir.islamtv",
  "extendedInfo": {
    "installSize": "5.4M",
    "downloadsCount": "1,000+",
    "downloadsCountText": "1,000 - 5,000",
    "description": "Islam TV is a Islamic live tv viewer application. It provides live streaming media of major and popular Islamic tv channels.New channels will be added periodically.If any of the streaming server is down let us know through email: info@codelixir.comStreaming servers go down for various reasons. Sometimes due to extreme loads, sometimes authentication problems; sometimes permanently and sometimes temporarily. Don't rate this application bad or comment harshly as we have no control over those streaming servers, the maximum we can do is to replace that server link with a new working one when available. So encourage us with nice comments and ratings.Features:☆ Nice responsive UI.☆ Auto channel list update.☆ No additional plugin, library required.Keyword:islam islamic arabic app tv channel live streaming livetv iptv",
    "reviews": [
      {
        "timestampMsec": "1377603623181",
        "starRating": "3",
        "title": "Pls add peace tv UK and USA English",
        "comment": "Please add UK and USA English peace tv to get 5 star.",
        "commentId": "gp:AOqpTOF9XwJ2AjCLyq5eYo0cAq4Z-nrfF6VGzg667wSx6QwjJz-MXKdSdtOBVWQxsipQR5DLV4uDRqQo254pZg",
        "author": "Mohammed Mortoja",
        "authorURL": "http://lh5.ggpht.com/RREE0f2gSFRq9Yi_umALXt_ML6nJbTYJ6TEsCJg-75c1TUjH4nqP0KNfOsDqxaa_CqY",
        "authorSecureURL": "https://lh5.ggpht.com/RREE0f2gSFRq9Yi_umALXt_ML6nJbTYJ6TEsCJg-75c1TUjH4nqP0KNfOsDqxaa_CqY"
      },
      {
        "timestampMsec": "1370935845425",
        "starRating": "5",
        "title": "S3",
        "comment": "Good!",
        "commentId": "gp:AOqpTOFaDNYVQbq5JrTFSu0PYCxT-4osyz7LszU56XqX0rOVSMtlttIgG1guzpQXCe46CnPTnQmCzuuQX6ClJQ",
        "author": "Md.Moazzem Hossain",
        "authorURL": "http://lh5.googleusercontent.com/-PUo8iZjLuG0/AAAAAAAAAAI/AAAAAAAAA74/WA9Sfh_H-oc/photo.jpg",
        "authorSecureURL": "https://lh5.googleusercontent.com/-PUo8iZjLuG0/AAAAAAAAAAI/AAAAAAAAA74/WA9Sfh_H-oc/photo.jpg"
      },
      {
        "timestampMsec": "1372979156023",
        "starRating": "5",
        "comment": "\\340\\246\\266\\340\\246\\276\\340\\246\\256\\340\\246\\277\\340\\246\\256 \\340\\246\\254\\340\\247\\201\\340\\246\\207\\340\\247\\237\\340\\246\\276 \\340\\246\\232\\340\\246\\244\\340\\247\\201\\340\\246\\260\\340\\246\\252\\340\\247\\201\\340\\246\\260 \\340\\246\\254\\340\\246\\277\\340\\246\\254\\340\\246\\276\\340\\246\\260\\340\\246\\277\\340\\247\\237\\340\\246\\276",
        "commentId": "gp:AOqpTOEIJZZn-1S3ULvFS5jtoB_yhUkENRDgXhivvC7QqLrg-IH1-usNCOmjpSWKzRlqhF7OCG3Om_qHzzhcGw",
        "author": "shamimor rhman buiaa",
        "authorURL": "http://lh5.googleusercontent.com/-6_3yvK6O6z4/AAAAAAAAAAI/AAAAAAAAC_c/bRnev6rkg3M/photo.jpg",
        "authorSecureURL": "https://lh5.googleusercontent.com/-6_3yvK6O6z4/AAAAAAAAAAI/AAAAAAAAC_c/bRnev6rkg3M/photo.jpg"
      }
    ],
    "permissions": [
      "android.permission.WAKE_LOCK",
      "android.permission.INTERNET",
      "android.permission.ACCESS_NETWORK_STATE",
      "android.permission.WRITE_EXTERNAL_STORAGE",
      "android.permission.READ_EXTERNAL_STORAGE"
    ]
  }
}
