{
  "title": "How to Draw: Cute Angels",
  "playStoreURL": "https://play.google.com/store/apps/details?id=com.drawgames.biz.angels",
  "category": "Education",
  "price": "Free",
  "datePublished": "September 3, 2013",
  "version": "1.02",
  "operatingSystems": "2.3 and up",
  "ratingsCount": "276",
  "rating": "4.619565",
  "contentRating": "Low Maturity",
  "creator": "Draw Action Studio",
  "creatorURL": "https://play.google.com/store/apps/details?id=com.drawgames.biz.angels",
  "extendedInfo": {
    "installSize": "9.0M",
    "downloadsCount": "5,000+",
    "downloadsCountText": "5,000 - 10,000",
    "description": "Would you like to have fun drawing cute and fun Angels? That is exactly what the How to Draw: Cute Angels app allows you to do. Add this latest offering in the series of drawing apps and never worry about boredom again!Drawing is fun, but traditionally not so fun to learn. Unless you can afford a private tutor, you usually have to take a class that requires you to adhere to a specific schedule.  The How to Draw: Cute Angels app makes learning to draw as easy and as flexible as possible. All you need to provide is time, medium, and environment in which you want to draw!The How to Draw: Cute Angels app includes a collection of tutorials for drawing of the nice and beautiful angels. Whether you like to draw lone angel or twins angels or even Angels with Animals - they all could be available in this app. You can choose one, two, three, or all of tham to draw. The choice is yours!The How to Draw: Cute Angels app makes learning to draw a snap by using mimicking, a method of drawing that is ideal for both beginners and advanced artists. Simply follow the step-by-step instructions provided for your selected person. You will learn to draw in no time!--- Cute Angels ---The following is a list of Angels that you can draw with the How to Draw: Cute Anels app: - how to draw Cute Angel - how to draw Angel with Rose - how to draw Twins Angels - how to draw Adorable Angel - how to draw Beautiful Angel - how to draw Pretty Angel - how to draw Angel with Seashell - how to draw Angel with Kitten - how to draw Angel in the Rain - how to draw Angel Friendship - how to draw Flying Angel - how to draw Angels with Puppy - how to draw Three Angels - how to draw Angel at Work - how to draw Angels with Animals--- Features ---The following is a list of the features that you can expect with the How to Draw: Cute Angels app:- Free to use!- Portable so you can learn to draw wherever you take your mobile device!- One of the largest collections of tutorials for drawing Angels in a single app!- Easy to follow step-by-step instructions for each tutorial!- Each tutorial associated with a rating so you can choose according to your drawing level!- Navigation controls that allow you to learn at your own pace!Try How to Draw: Cute Angels!",
    "reviews": [
      {
        "timestampMsec": "1378549948809",
        "starRating": "5",
        "comment": "Supper !!!!!!!!!!!!!!!!!!!!!!!!!!!!!!!!!!!!!!!!!!!!!!!!!!!!!!!!!!!!!!!!!!!!!!!!!!!!!!!!!!!!!!!!!!!!!!!!",
        "commentId": "gp:AOqpTOEi7a1zCsyov_uqWVz_-e5E_veN8Ie7VdeAIzpdtTYUZ6crGkNT3Lhs4HxNmI1F3fs576WDM9aXj1YSFiE",
        "author": "Caitlin Clay",
        "authorURL": "http://lh5.ggpht.com/RREE0f2gSFRq9Yi_umALXt_ML6nJbTYJ6TEsCJg-75c1TUjH4nqP0KNfOsDqxaa_CqY",
        "authorSecureURL": "https://lh5.ggpht.com/RREE0f2gSFRq9Yi_umALXt_ML6nJbTYJ6TEsCJg-75c1TUjH4nqP0KNfOsDqxaa_CqY"
      },
      {
        "timestampMsec": "1376802611135",
        "starRating": "5",
        "title": "So cute!",
        "comment": "I love angels and I love drawing and OMG they are so cute. Simply awesome",
        "commentId": "gp:AOqpTOEd16x7YrX13RfqZxYGlXIUVYwENEZ_Mq92H7rmzJSyS9YuMbA08x6Xb2ENHMTaFWfQGpQM8LyJhdTr2h8",
        "author": "Brittany Steckly",
        "authorURL": "http://lh5.ggpht.com/RREE0f2gSFRq9Yi_umALXt_ML6nJbTYJ6TEsCJg-75c1TUjH4nqP0KNfOsDqxaa_CqY",
        "authorSecureURL": "https://lh5.ggpht.com/RREE0f2gSFRq9Yi_umALXt_ML6nJbTYJ6TEsCJg-75c1TUjH4nqP0KNfOsDqxaa_CqY"
      },
      {
        "timestampMsec": "1378086113726",
        "starRating": "3",
        "title": "It shows how to draw adorable angels step by step.",
        "comment": "It could use something else but I don\\'t know what.",
        "commentId": "gp:AOqpTOEIEOiTX7-dVo42cStqtqJ6XG4QhTCIDas-vgqYs56iT_F6C3JIkXgxnnAXwuF8326iW52fxBB5mOFYeZA",
        "author": "Amber Cloyd",
        "authorURL": "http://lh5.ggpht.com/RREE0f2gSFRq9Yi_umALXt_ML6nJbTYJ6TEsCJg-75c1TUjH4nqP0KNfOsDqxaa_CqY",
        "authorSecureURL": "https://lh5.ggpht.com/RREE0f2gSFRq9Yi_umALXt_ML6nJbTYJ6TEsCJg-75c1TUjH4nqP0KNfOsDqxaa_CqY"
      },
      {
        "timestampMsec": "1377740788811",
        "starRating": "5",
        "title": "Cute!",
        "comment": "Cutest drawings ever",
        "commentId": "gp:AOqpTOEpKikfZ7fBUnPTXtIzO-Ivni99qGXfN_vgF7w-4F40pwZ_LY9tOSnUXl7DptCaeotHcPpglWJ-YTjDUDg",
        "author": "Jonathan Rivera",
        "authorURL": "http://lh5.ggpht.com/RREE0f2gSFRq9Yi_umALXt_ML6nJbTYJ6TEsCJg-75c1TUjH4nqP0KNfOsDqxaa_CqY",
        "authorSecureURL": "https://lh5.ggpht.com/RREE0f2gSFRq9Yi_umALXt_ML6nJbTYJ6TEsCJg-75c1TUjH4nqP0KNfOsDqxaa_CqY"
      },
      {
        "timestampMsec": "1378048048949",
        "starRating": "3",
        "title": "Nice app",
        "comment": "Nice app wish it had more though",
        "commentId": "gp:AOqpTOFfz1EqWxZo3u_qwbVrDyOPIGH5MrhaA4q0Kg4vVHiC_UjcYG21INJ-Jdq5nQ9oKzg_ml3dEb3OQ8gWhng",
        "author": "Jocelyn Rosales",
        "authorURL": "http://lh5.ggpht.com/RREE0f2gSFRq9Yi_umALXt_ML6nJbTYJ6TEsCJg-75c1TUjH4nqP0KNfOsDqxaa_CqY",
        "authorSecureURL": "https://lh5.ggpht.com/RREE0f2gSFRq9Yi_umALXt_ML6nJbTYJ6TEsCJg-75c1TUjH4nqP0KNfOsDqxaa_CqY"
      },
      {
        "timestampMsec": "1376218186658",
        "starRating": "3",
        "title": "Easy to follow...",
        "comment": "Nyc app...",
        "commentId": "gp:AOqpTOHTaowYFgdyyedkAkChW9LRaZTJDkVGmJa2cdvqXigU56en2DrQ6cY2hsMBA3MxkYSa_ltlK1V3_OlUosU",
        "author": "Jonesca Fernandes",
        "authorURL": "http://lh5.ggpht.com/RREE0f2gSFRq9Yi_umALXt_ML6nJbTYJ6TEsCJg-75c1TUjH4nqP0KNfOsDqxaa_CqY",
        "authorSecureURL": "https://lh5.ggpht.com/RREE0f2gSFRq9Yi_umALXt_ML6nJbTYJ6TEsCJg-75c1TUjH4nqP0KNfOsDqxaa_CqY"
      },
      {
        "timestampMsec": "1378080262006",
        "starRating": "5",
        "title": "Good",
        "comment": "Excellent",
        "commentId": "gp:AOqpTOFSGhMVq1WShieBgrEVtxEcwzQFq2QpRSzL6pVYqlmKDZRA4IUDr2CgR0SNpUC2JB6JkU5KAUGue4if8dw",
        "author": "Lisbeth Falero",
        "authorURL": "http://lh5.ggpht.com/RREE0f2gSFRq9Yi_umALXt_ML6nJbTYJ6TEsCJg-75c1TUjH4nqP0KNfOsDqxaa_CqY",
        "authorSecureURL": "https://lh5.ggpht.com/RREE0f2gSFRq9Yi_umALXt_ML6nJbTYJ6TEsCJg-75c1TUjH4nqP0KNfOsDqxaa_CqY"
      },
      {
        "timestampMsec": "1377473284751",
        "starRating": "5",
        "title": "Excellent",
        "comment": "Excellent",
        "commentId": "gp:AOqpTOEn8QqF7-2eJP-S_dAJKWY6vDvO4fwVw0ZFbLlyOUui4ymGpO23tOCyBimZTnHiDs1WvxLzXChsWeci5AQ",
        "author": "Sara Melendrez",
        "authorURL": "http://lh5.googleusercontent.com/-A6NlSQb_Pzg/AAAAAAAAAAI/AAAAAAAAABM/tY41z3Yoe5Y/photo.jpg",
        "authorSecureURL": "https://lh5.googleusercontent.com/-A6NlSQb_Pzg/AAAAAAAAAAI/AAAAAAAAABM/tY41z3Yoe5Y/photo.jpg"
      },
      {
        "timestampMsec": "1377773167441",
        "starRating": "5",
        "title": "golly gosh....",
        "comment": "they are amazingly awesomely cute i say bravo:-)",
        "commentId": "gp:AOqpTOGXpqUCvcBi7zCFGPRQ0-VCV7Znsj8fyUcfrk_n2T0c1ZLw0gCXkrEZ6qX6KNpSaBg4fQNib62IQAkzTys",
        "author": "ziafat abbassi",
        "authorURL": "http://lh5.ggpht.com/RREE0f2gSFRq9Yi_umALXt_ML6nJbTYJ6TEsCJg-75c1TUjH4nqP0KNfOsDqxaa_CqY",
        "authorSecureURL": "https://lh5.ggpht.com/RREE0f2gSFRq9Yi_umALXt_ML6nJbTYJ6TEsCJg-75c1TUjH4nqP0KNfOsDqxaa_CqY"
      },
      {
        "timestampMsec": "1377221156364",
        "starRating": "5",
        "title": "Thanks",
        "comment": "Now that I have this app I am better at drawing",
        "commentId": "gp:AOqpTOEDY3Q1eEC69CZpqVXkg0QnCuAh-MC_loStFHGShM6h0nTR5w4fg57g0bC7SZvK3ryo4yWQv7aeuxv0nDM",
        "author": "Nicole Nicolas",
        "authorURL": "http://lh6.googleusercontent.com/-3FcHQLjk8No/AAAAAAAAAAI/AAAAAAAAABM/wjriS1UyseY/photo.jpg",
        "authorSecureURL": "https://lh6.googleusercontent.com/-3FcHQLjk8No/AAAAAAAAAAI/AAAAAAAAABM/wjriS1UyseY/photo.jpg"
      },
      {
        "timestampMsec": "1377983577585",
        "starRating": "5",
        "title": "Yasmin",
        "comment": "Love Angels , fantastic !",
        "commentId": "gp:AOqpTOHGj0eWbzVv4p0yfWgQCc2mNUoj2KxClfd7i6MlScme5U3aqoMYg67LCbaD6K5UoO9ohPFZ5FDhTUMKlCk",
        "author": "Yasmin Smith",
        "authorURL": "http://lh5.ggpht.com/RREE0f2gSFRq9Yi_umALXt_ML6nJbTYJ6TEsCJg-75c1TUjH4nqP0KNfOsDqxaa_CqY",
        "authorSecureURL": "https://lh5.ggpht.com/RREE0f2gSFRq9Yi_umALXt_ML6nJbTYJ6TEsCJg-75c1TUjH4nqP0KNfOsDqxaa_CqY"
      },
      {
        "timestampMsec": "1377270313258",
        "starRating": "5",
        "title": "So cute angels",
        "comment": "This is very amazing app",
        "commentId": "gp:AOqpTOFuy5HOe4hq87fiy_RduG3oxF46HOQqUolUYusYqk2VHERAIKRb6-0jT_BRK0rTF5mvMq59bh8Lzpw2zQk",
        "author": "Dyreen Griziele Garcia Villamar",
        "authorURL": "http://lh5.ggpht.com/RREE0f2gSFRq9Yi_umALXt_ML6nJbTYJ6TEsCJg-75c1TUjH4nqP0KNfOsDqxaa_CqY",
        "authorSecureURL": "https://lh5.ggpht.com/RREE0f2gSFRq9Yi_umALXt_ML6nJbTYJ6TEsCJg-75c1TUjH4nqP0KNfOsDqxaa_CqY"
      },
      {
        "timestampMsec": "1378156461497",
        "starRating": "4",
        "title": "Excellent",
        "comment": "This app could teach anyone to draw angels all you need is apps of most things but done the same way if always been into drawing a this is great",
        "commentId": "gp:AOqpTOHw3qO7mfr-OOJkAXhhdYIscpZAmhOQKzrzFoOQboqUzxVeHP3YAGCaBjovvOTsRHMDwWddFAV-5BYxnmM",
        "author": "Simon Poole",
        "authorURL": "http://lh5.ggpht.com/RREE0f2gSFRq9Yi_umALXt_ML6nJbTYJ6TEsCJg-75c1TUjH4nqP0KNfOsDqxaa_CqY",
        "authorSecureURL": "https://lh5.ggpht.com/RREE0f2gSFRq9Yi_umALXt_ML6nJbTYJ6TEsCJg-75c1TUjH4nqP0KNfOsDqxaa_CqY"
      },
      {
        "timestampMsec": "1377485135632",
        "starRating": "3",
        "title": ".",
        "comment": "Its good I guess",
        "commentId": "gp:AOqpTOEVxmXAduW6YMMN3Ukfkuc_ySNjtduAkFjZ4ObF7xU7Q_wfQAUUYNEjckdlM7MSuEdwuk4IxABZLTNGa3k",
        "author": "Jaime White",
        "authorURL": "http://lh3.googleusercontent.com/-_U2JsDFGk-Y/AAAAAAAAAAI/AAAAAAAAADg/QUkz3UEvouY/photo.jpg",
        "authorSecureURL": "https://lh3.googleusercontent.com/-_U2JsDFGk-Y/AAAAAAAAAAI/AAAAAAAAADg/QUkz3UEvouY/photo.jpg"
      },
      {
        "timestampMsec": "1376984735186",
        "starRating": "5",
        "title": "Love it",
        "comment": "Best game ever",
        "commentId": "gp:AOqpTOE5pShgOh-5kgFoLobN29WaS2fcL9pgCQXw_kf3zft1si_fqTvcDV3XTRHXS2uTeT3mxSUFJSGp40M4G6w",
        "author": "Alicia Manga",
        "authorURL": "http://lh5.googleusercontent.com/-OB6RDl6oBRE/AAAAAAAAAAI/AAAAAAAACd8/PoNBTkKPvDE/photo.jpg",
        "authorSecureURL": "https://lh5.googleusercontent.com/-OB6RDl6oBRE/AAAAAAAAAAI/AAAAAAAACd8/PoNBTkKPvDE/photo.jpg"
      },
      {
        "timestampMsec": "1376211323704",
        "starRating": "5",
        "title": "I like it",
        "comment": "Love it!",
        "commentId": "gp:AOqpTOFv8HUTa0Ua4a1xxRsT8jrquDeSvMyueOAu_9zWakoyKk7n3O98E3_PAKxn5vTd70DWDgTzunVcloXC_DQ",
        "author": "Cherry G",
        "authorURL": "http://lh3.googleusercontent.com/-C2lfQXKPf8o/AAAAAAAAAAI/AAAAAAAAAGA/Le79aSC9u6U/photo.jpg",
        "authorSecureURL": "https://lh3.googleusercontent.com/-C2lfQXKPf8o/AAAAAAAAAAI/AAAAAAAAAGA/Le79aSC9u6U/photo.jpg"
      },
      {
        "timestampMsec": "1376808596022",
        "starRating": "5",
        "title": "Excellebt",
        "comment": "Great app",
        "commentId": "gp:AOqpTOHMXDHInxDRTR2TAaXe8Lc_276ZQRVGJ1XZ5NwF6f5f0skfSpNf5LrpMte6hr61k19TDcba5QlU4dPE8cs",
        "author": "Pedro Leos",
        "authorURL": "http://lh5.ggpht.com/RREE0f2gSFRq9Yi_umALXt_ML6nJbTYJ6TEsCJg-75c1TUjH4nqP0KNfOsDqxaa_CqY",
        "authorSecureURL": "https://lh5.ggpht.com/RREE0f2gSFRq9Yi_umALXt_ML6nJbTYJ6TEsCJg-75c1TUjH4nqP0KNfOsDqxaa_CqY"
      },
      {
        "timestampMsec": "1376464204876",
        "starRating": "5",
        "title": "I love it",
        "comment": "The angels are so cute and easy to draw",
        "commentId": "gp:AOqpTOHpC62UmKnpmaRf3GxJwFOLtIYpfT7K8Hxl8_ebOlHXEbT9AJWEkAIuMLOf1YYFU6AccbgRADK14tE-XPs",
        "author": "Marlene Delgado",
        "authorURL": "http://lh5.ggpht.com/RREE0f2gSFRq9Yi_umALXt_ML6nJbTYJ6TEsCJg-75c1TUjH4nqP0KNfOsDqxaa_CqY",
        "authorSecureURL": "https://lh5.ggpht.com/RREE0f2gSFRq9Yi_umALXt_ML6nJbTYJ6TEsCJg-75c1TUjH4nqP0KNfOsDqxaa_CqY"
      },
      {
        "timestampMsec": "1376293149241",
        "starRating": "5",
        "title": "Now learn how to draw angles",
        "comment": "I luv this app",
        "commentId": "gp:AOqpTOHJZHycXPGM4ldmMptq-DEEbJx38oKsbHwlVggvsuSkenCZAOBUKyNtYRIr7Z5ObGxKzKY2Q16KL7AWqJ4",
        "author": "Jenifer Chagala",
        "authorURL": "http://lh5.googleusercontent.com/-S0D2bre4qzk/AAAAAAAAAAI/AAAAAAAABYg/3QjiLVEbTvU/photo.jpg",
        "authorSecureURL": "https://lh5.googleusercontent.com/-S0D2bre4qzk/AAAAAAAAAAI/AAAAAAAABYg/3QjiLVEbTvU/photo.jpg"
      },
      {
        "timestampMsec": "1376328977536",
        "starRating": "5",
        "comment": "I love o draw im back to the drawing  love the app",
        "commentId": "gp:AOqpTOHSe1aUXzfzCuz3RlEeiu55j5mJCiFtJyVMVIUU-rQ_Gn6trI5ISS-lgF4b-PlFHY6dhB99PWBKXoNc3bk",
        "author": "Evelyn Ruffini",
        "authorURL": "http://lh3.googleusercontent.com/-q-sNVes6j20/AAAAAAAAAAI/AAAAAAAAATU/TsFYUDPV4J0/photo.jpg",
        "authorSecureURL": "https://lh3.googleusercontent.com/-q-sNVes6j20/AAAAAAAAAAI/AAAAAAAAATU/TsFYUDPV4J0/photo.jpg"
      }
    ],
    "permissions": [
      "android.permission.INTERNET",
      "android.permission.ACCESS_NETWORK_STATE",
      "android.permission.READ_PHONE_STATE",
      "android.permission.GET_ACCOUNTS",
      "android.permission.ACCESS_COARSE_LOCATION",
      "android.permission.ACCESS_FINE_LOCATION",
      "android.permission.ACCESS_WIFI_STATE",
      "com.android.browser.permission.READ_HISTORY_BOOKMARKS",
      "com.android.launcher.permission.INSTALL_SHORTCUT"
    ]
  }
}
